FastaDist-1.0.1.dist-info/METADATA
FastaDist-1.0.1.dist-info/RECORD
FastaDist-1.0.1.dist-info/WHEEL
FastaDist-1.0.1.dist-info/entry_points.txt
FastaDist-1.0.1.dist-info/top_level.txt
fastadist/__init__.py
fastadist/fastadist_functions.py
fastadist/run_fastadist.py
