Metadata-Version: 2.1
Name: FastaDist
Version: 1.0.1
Summary: Package to calculate a distance matrix from a multiple sequence file
Home-page: UNKNOWN
Author: Anthony Underwood
Author-email: au3@sanger.ac.uk
License: MIT
Platform: UNKNOWN
Classifier: Development Status :: 3 - Alpha
Classifier: Intended Audience :: Science/Research
Classifier: License :: OSI Approved :: MIT License
Classifier: Programming Language :: Python :: 3
Requires-Python: >=3
License-File: LICENSE
Requires-Dist: biopython
Requires-Dist: bitarray
Requires-Dist: parmap
Requires-Dist: tqdm
Requires-Dist: dendropy
